pyraftlog/__init__.py
pyraftlog/exceptions.py
pyraftlog/httpd.py
pyraftlog/log.py
pyraftlog/message.py
pyraftlog/migrate.py
pyraftlog/mock.py
pyraftlog/node.py
pyraftlog/state.py
pyraftlog/statistics.py
pyraftlog/storage.py
pyraftlog/transport.py
pyraftlog-3.0.0.dist-info/METADATA
pyraftlog-3.0.0.dist-info/WHEEL
pyraftlog-3.0.0.dist-info/entry_points.txt
pyraftlog-3.0.0.dist-info/top_level.txt
pyraftlog-3.0.0.dist-info/RECORD
