Metadata-Version: 2.1
Name: pyraftlog
Version: 3.0.0
Summary: Pure Python implementation of the RAFT consensus algorithm
Home-page: https://pypi.org/project/pyraftlog/
Download-URL: https://pypi.org/project/pyraftlog/
Author: Peter Scopes
Author-email: peter.scopes@nccgroup.com
Maintainer: Peter Scopes
Maintainer-email: peter.scopes@nccgroup.com
License: Copyright 2018 NCC
Keywords: raft,consensus
Classifier: Programming Language :: Python :: 3
Classifier: Programming Language :: Python :: 3.6
Classifier: Programming Language :: Python :: 3.7
Classifier: Programming Language :: Python :: 3.8
Classifier: Programming Language :: Python :: 3.9
Classifier: Programming Language :: Python :: 3.10
Classifier: Operating System :: OS Independent
Requires-Python: >=3.6
Requires-Dist: msgpack (>="0.6.1")
Requires-Dist: redis (>="3.0.0")
